{"id":797,"name":"password-lost-form","title":"Password Lost Form","date":"2023-04-23 12:22:58","date_formatted":"Apr 23, 2023","author":{"name":"Eric Chong","avatar":"https:\/\/secure.gravatar.com\/avatar\/8e40925472a60f9c476ed96312c7a56e?s=60&d=mm&r=g","url":"https:\/\/anything.local"},"permalink":"https:\/\/anything.local\/template\/password-lost-form\/","thumbnail":false,"bundles":[],"tags":[],"type":"section","content":[{"id":"uysexh","name":"section","parent":0,"children":["mmrxda"],"settings":[]},{"id":"mmrxda","name":"container","parent":"uysexh","children":["jqfwxv"],"settings":{"_direction":"row","_alignSelf":"center","_justifyContent":"center","_alignItems":"center","_height":"100vh"}},{"id":"jqfwxv","name":"block","parent":"mmrxda","children":["hgvrdv","aazzkp","uxrwnz"],"settings":{"_width":"340px","_padding":{"top":"25","bottom":"25","right":"25","left":"25"},"_border":{"radius":{"top":"8","right":"8","bottom":"8","left":"8"},"width":{"top":"0","bottom":"0","left":"0","right":"0"},"style":"none"},"_boxShadow":{"values":{"offsetY":"7","blur":"30","spread":"-10"},"color":{"hex":"#96aab4","rgb":"rgba(150, 170, 180, 0.5)","hsl":"hsla(200, 17%, 65%, 0.5)"}}}},{"id":"hgvrdv","name":"heading","parent":"jqfwxv","children":[],"settings":{"text":"Forgot Your Password?","tag":"custom","_typography":{"color":{"hex":"#212121","id":"ab6da8","name":"Color #6"},"font-family":"custom_font_34","font-weight":"700","line-height":"1.5","font-size":"26"}}},{"id":"aazzkp","name":"text-basic","parent":"jqfwxv","children":[],"settings":{"text":"If you forgot your password, no worries. Enter your email address and we'll send you a link to reset your password.","_padding":{"top":"20","bottom":"40"},"_typography":{"color":{"hex":"#212121","id":"ab6da8","name":"Color #6"},"font-size":"14","font-family":"custom_font_34","font-weight":"400","line-height":"1.5"}}},{"id":"uxrwnz","name":"form","parent":"jqfwxv","children":[],"settings":{"fields":[{"type":"email","label":"Email","placeholder":"Your Email","required":true,"id":"33ac0d"}],"submitButtonStyle":"primary","successMessage":"Password reset request submitted successfully. Please check your email and follow the instruction to reset your password. You will be redirect back to login page in 5s.","emailSubject":"Contact form request","emailTo":"admin_email","fromName":"Any","emailErrorMessage":"Submission failed. Please reload the page and try to submit the form again.","htmlEmail":true,"mailchimpPendingMessage":"Please check your email to confirm your subscription.","mailchimpErrorMessage":"Sorry, but we could not subscribe you.","sendgridErrorMessage":"Sorry, but we could not subscribe you.","_cssClasses":"password-lost-form","requiredAsterisk":true,"showLabels":true,"labelTypography":{"color":{"hex":"#212121","id":"ab6da8","name":"Color #6"},"font-size":"14","font-family":"custom_font_34","font-weight":"400","line-height":"1.5"},"placeholderTypography":{"color":{"hex":"#9e9e9e","id":"7c689c","name":"Color #3"},"font-size":"16","font-family":"custom_font_34","font-weight":"400","line-height":"1.5"},"fieldBackgroundColor":{"hex":"#f8f8f8"},"fieldBorder":{"radius":{"top":"4","right":"4","bottom":"4","left":"4"}},"fieldTypography":{"color":{"hex":"#212121","id":"ab6da8","name":"Color #6"},"font-size":"16","font-family":"custom_font_34","font-weight":"400","line-height":"40px"},"submitButtonText":"Reset Password","submitButtonTypography":{"font-size":"16","font-family":"custom_font_34","font-weight":"400","line-height":"1.5","color":{"hex":"#ffffff"}},"submitButtonBackgroundColor":{"hex":"#ff9800","id":"28009b","name":"Color #9"},"submitButtonBorder":{"radius":{"top":"4","right":"4","bottom":"4","left":"4"}},"actions":["custom"]}}],"templateType":"section"}